pyfcg/__init__.py
pyfcg/agent.py
pyfcg/cxn.py
pyfcg/fcg_go_bridge.py
pyfcg/grammar.py
pyfcg/propbank.py
pyfcg/resources.py
pyfcg/routes.py
pyfcg/utils.py
pyfcg/web_interface.py
pyfcg-3.1.dist-info/licenses/LICENSE
pyfcg-3.1.dist-info/METADATA
pyfcg-3.1.dist-info/WHEEL
pyfcg-3.1.dist-info/top_level.txt
pyfcg-3.1.dist-info/RECORD
