Metadata-Version: 2.4
Name: pyfcg
Version: 3.1
Summary: A Python port of Fluid Construction Grammar
License-File: LICENSE
Requires-Dist: wget==3.2
Requires-Dist: requests==2.32.3
Requires-Dist: platformdirs
Requires-Dist: penman
Dynamic: description
Dynamic: description-content-type
Dynamic: license-file
Dynamic: requires-dist
Dynamic: summary
